xtmigrations/__init__.py
xtmigrations/__main__.py
xtmigrations/migrate.py
xtmigrations/config/db.cnf
xtmigrations/sql/base/init_postgresql.sql
xtmigrations/utils/__init__.py
xtmigrations/utils/migrate_utils.py
xtmigrations-1.0.3.dist-info/LICENSE
xtmigrations-1.0.3.dist-info/METADATA
xtmigrations-1.0.3.dist-info/WHEEL
xtmigrations-1.0.3.dist-info/entry_points.txt
xtmigrations-1.0.3.dist-info/top_level.txt
xtmigrations-1.0.3.dist-info/RECORD
