Metadata-Version: 2.1
Name: xtmigrations
Version: 1.0.3
Summary: Fast and easy to use database migration tool for Postgresql, written in Python
Home-page: https://github.com/startechm/xtmigrations
Author: Startech M
Author-email: startechm@proton.me
License: Apache license 2.0
Keywords: XTMigrations migration sql db upgrade
License-File: LICENSE
Requires-Dist: psycopg2
